src/__init__.py
src/pmec.py
pmec-0.0.4.dist-info/LICENSE.txt
pmec-0.0.4.dist-info/METADATA
pmec-0.0.4.dist-info/WHEEL
pmec-0.0.4.dist-info/top_level.txt
pmec-0.0.4.dist-info/RECORD
